binary_tools/__init__.py
binary_tools/binary_util.py
binary_tools/bit_encoder.py
binary_tools/byte_encoder.py
binary_tools-0.2.0.dist-info/LICENSE
binary_tools-0.2.0.dist-info/METADATA
binary_tools-0.2.0.dist-info/WHEEL
binary_tools-0.2.0.dist-info/top_level.txt
binary_tools-0.2.0.dist-info/RECORD
